mobileproxy/__init__.py
mobileproxy/_async.py
mobileproxy-1.0.5.dist-info/licenses/LICENSE
mobileproxy-1.0.5.dist-info/METADATA
mobileproxy-1.0.5.dist-info/WHEEL
mobileproxy-1.0.5.dist-info/top_level.txt
mobileproxy-1.0.5.dist-info/RECORD
