Metadata-Version: 2.4
Name: mobileproxy
Version: 1.0.5
Summary: Unofficial python library for working with mobileproxy.space
Home-page: https://github.com/makarworld/mobileproxy.git
Download-URL: https://github.com/makarworld/mobileproxy/archive/refs/tags/v1.0.5.zip
Author: abuztrade
Author-email: abuztrade.work@gmail.com
License: MIT License
Classifier: Development Status :: 4 - Beta
Classifier: Topic :: Communications :: Email
Classifier: Operating System :: OS Independent
Classifier: License :: OSI Approved :: MIT License
Classifier: Programming Language :: Python :: 3.10
Classifier: Intended Audience :: Developers
Classifier: Intended Audience :: Customer Service
Classifier: Intended Audience :: Financial and Insurance Industry
Requires-Python: >=3.10.0
License-File: LICENSE
Requires-Dist: requests
Requires-Dist: curl_cffi
Dynamic: author
Dynamic: author-email
Dynamic: classifier
Dynamic: description
Dynamic: description-content-type
Dynamic: download-url
Dynamic: home-page
Dynamic: license
Dynamic: license-file
Dynamic: requires-dist
Dynamic: requires-python
Dynamic: summary
